odoo/addons/stock_release_channel_partner_public_holidays/README.rst
odoo/addons/stock_release_channel_partner_public_holidays/__init__.py
odoo/addons/stock_release_channel_partner_public_holidays/__manifest__.py
odoo/addons/stock_release_channel_partner_public_holidays/i18n/fr.po
odoo/addons/stock_release_channel_partner_public_holidays/i18n/it.po
odoo/addons/stock_release_channel_partner_public_holidays/i18n/stock_release_channel_partner_public_holidays.pot
odoo/addons/stock_release_channel_partner_public_holidays/models/__init__.py
odoo/addons/stock_release_channel_partner_public_holidays/models/stock_picking.py
odoo/addons/stock_release_channel_partner_public_holidays/models/stock_release_channel.py
odoo/addons/stock_release_channel_partner_public_holidays/readme/CONTRIBUTORS.rst
odoo/addons/stock_release_channel_partner_public_holidays/readme/CREDIT.rst
odoo/addons/stock_release_channel_partner_public_holidays/readme/DESCRIPTION.rst
odoo/addons/stock_release_channel_partner_public_holidays/readme/USAGE.rst
odoo/addons/stock_release_channel_partner_public_holidays/static/description/channel_form.png
odoo/addons/stock_release_channel_partner_public_holidays/static/description/icon.png
odoo/addons/stock_release_channel_partner_public_holidays/static/description/index.html
odoo/addons/stock_release_channel_partner_public_holidays/tests/__init__.py
odoo/addons/stock_release_channel_partner_public_holidays/tests/test_release_on_holiday.py
odoo/addons/stock_release_channel_partner_public_holidays/views/stock_release_channel.xml
odoo_addon_stock_release_channel_partner_public_holidays-16.0.2.1.0.dist-info/METADATA
odoo_addon_stock_release_channel_partner_public_holidays-16.0.2.1.0.dist-info/WHEEL
odoo_addon_stock_release_channel_partner_public_holidays-16.0.2.1.0.dist-info/top_level.txt
odoo_addon_stock_release_channel_partner_public_holidays-16.0.2.1.0.dist-info/RECORD
