Metadata-Version: 2.1
Name: odoo-addon-stock_release_channel_partner_public_holidays
Version: 16.0.2.1.0
Summary: Add an option to exclude the public holidays when assigning th release channel
Home-page: https://github.com/OCA/wms
Author: Camptocamp, BCIM, Odoo Community Association (OCA)
Author-email: support@odoo-community.org
License: AGPL-3
Classifier: Programming Language :: Python
Classifier: Framework :: Odoo
Classifier: Framework :: Odoo :: 16.0
Classifier: License :: OSI Approved :: GNU Affero General Public License v3
Requires-Python: >=3.10
Requires-Dist: odoo-addon-hr-holidays-public<16.1dev,>=16.0dev
Requires-Dist: odoo-addon-stock-release-channel-shipment-lead-time<16.1dev,>=16.0dev
Requires-Dist: odoo<16.1dev,>=16.0a
